MANIFEST.in
setup.py
globenet/__init__.py
globenet/exceptions.py
globenet/web.py
globenet.egg-info/PKG-INFO
globenet.egg-info/SOURCES.txt
globenet.egg-info/dependency_links.txt
globenet.egg-info/entry_points.txt
globenet.egg-info/not-zip-safe
globenet.egg-info/requires.txt
globenet.egg-info/top_level.txt
globenet/paste/__init__.py
globenet/paste/templates.py
globenet/paste/controller/+controller+.py_tmpl
globenet/paste/controller/__init__.py
globenet/paste/controller/templates/+controller+.html
globenet/paste/project/.local.py.swp
globenet/paste/project/app.yaml_tmpl
globenet/paste/project/bootstrap.py
globenet/paste/project/config.ini
globenet/paste/project/create-bootstrap.py
globenet/paste/project/main.py_tmpl
globenet/paste/project/setup.py_tmpl
globenet/paste/project/+package+.egg-info/entry_points.txt_tmpl
globenet/paste/project/patches/__init__.py
globenet/paste/project/patches/__init__.pyc
globenet/paste/project/patches/pkg_resources.py
globenet/paste/project/patches/pkg_resources.pyc
globenet/paste/project/templates/index.html