Metadata-Version: 1.0
Name: globenet
Version: 0.2
Summary: Lightweight web framework for Google(tm) App Engine
Home-page: http://code.google.com/p/globenet/
Author: Tristan Straub
Author-email: tristanstraub@gmail.com
License: UNKNOWN
Platform: UNKNOWN
